urlfinderlib/__init__.py
urlfinderlib/__main__.py
urlfinderlib/finders/__init__.py
urlfinderlib/finders/csv.py
urlfinderlib/finders/data.py
urlfinderlib/finders/html.py
urlfinderlib/finders/ical.py
urlfinderlib/finders/pdf.py
urlfinderlib/finders/text.py
urlfinderlib/finders/xml.py
urlfinderlib/helpers.py
urlfinderlib/tokenizer/__init__.py
urlfinderlib/tokenizer/tokenizer.py
urlfinderlib/url.py
urlfinderlib/urlfinderlib.py
urlfinderlib-0.19.0.dist-info/WHEEL
urlfinderlib-0.19.0.dist-info/entry_points.txt
urlfinderlib-0.19.0.dist-info/METADATA
urlfinderlib-0.19.0.dist-info/RECORD
