Metadata-Version: 2.4
Name: urlfinderlib
Version: 0.19.0
Summary: Library to find URLs and check their validity.
Keywords: url,urlfinderlib
Author: Matthew Wilson
Author-email: Matthew Wilson <dev@bytecafe.io>
License-Expression: Apache-2.0
Classifier: Development Status :: 3 - Alpha
Classifier: Intended Audience :: Developers
Classifier: Topic :: Software Development :: Libraries :: Python Modules
Classifier: License :: OSI Approved :: Apache Software License
Classifier: Programming Language :: Python :: 3
Classifier: Programming Language :: Python :: 3.10
Classifier: Programming Language :: Python :: 3.11
Classifier: Programming Language :: Python :: 3.12
Classifier: Programming Language :: Python :: 3.13
Requires-Dist: icalendar>=6.3.2
Requires-Dist: idna>=3.11
Requires-Dist: lxml>=6.0.2
Requires-Dist: python-magic>=0.4.27
Requires-Dist: tld>=0.13.1
Requires-Dist: validators>=0.35.0
Requires-Python: >=3.10
Project-URL: Homepage, https://github.com/ace-ecosystem/urlfinderlib
Project-URL: Repository, https://github.com/ace-ecosystem/urlfinderlib
